picodaq/__init__.py
picodaq/adc.py
picodaq/binreader.py
picodaq/binwriter.py
picodaq/dac.py
picodaq/decorators.py
picodaq/device.py
picodaq/errors.py
picodaq/mockstim.py
picodaq/stimulus.py
picodaq/stream.py
picodaq/units.py
picodaq/utils.py
picodaq-0.1.0.dist-info/LICENSE
picodaq-0.1.0.dist-info/METADATA
picodaq-0.1.0.dist-info/WHEEL
picodaq-0.1.0.dist-info/top_level.txt
picodaq-0.1.0.dist-info/RECORD
