Metadata-Version: 2.2
Name: picodaq
Version: 0.1.0
Summary: Python library for picoDAQ data acquisition
Author-email: Daniel Wagenaar <daw@caltech.edu>
Project-URL: Homepage, https://github.com/wagenadl/picodaq
Classifier: Programming Language :: Python :: 3
Classifier: License :: OSI Approved :: GNU General Public License v3 or later (GPLv3+)
Classifier: Operating System :: OS Independent
Requires-Python: >=3.8
License-File: LICENSE
Requires-Dist: numpy
Requires-Dist: scipy
Requires-Dist: pyqt5
